testah995q/__init__.py
testah995q/core.py
testah995q-0.1.1.dist-info/METADATA
testah995q-0.1.1.dist-info/WHEEL
testah995q-0.1.1.dist-info/top_level.txt
testah995q-0.1.1.dist-info/RECORD
